valdata/__init__.py
valdata/auxiliary.py
valdata/utils.py
valdata/validation.py
valdata/visuals.py
valdata-0.0.2.dist-info/LICENSE
valdata-0.0.2.dist-info/METADATA
valdata-0.0.2.dist-info/WHEEL
valdata-0.0.2.dist-info/top_level.txt
valdata-0.0.2.dist-info/RECORD
