Metadata-Version: 2.1
Name: valdata
Version: 0.0.2
Summary: A Python package for validating data consistency
Home-page: https://github.com/GabrielGod1/valdata
Author: GabrielGod1
Author-email: altGeneric@hotmail.com
Classifier: Programming Language :: Python :: 3
Classifier: License :: OSI Approved :: BSD License
Classifier: Operating System :: OS Independent
Requires-Python: >=3.6
License-File: LICENSE
Requires-Dist: pandas >=1.5.2
Requires-Dist: numpy >=1.22.4
Requires-Dist: pyspark >=3.1.1
Requires-Dist: pytz >=2024.1
Requires-Dist: tabulate >=0.9.0
Requires-Dist: IPython >=8.18.1
